firstmodul/output.py
MyFirstPypi_pshpjr-0.1.dist-info/METADATA
MyFirstPypi_pshpjr-0.1.dist-info/WHEEL
MyFirstPypi_pshpjr-0.1.dist-info/top_level.txt
MyFirstPypi_pshpjr-0.1.dist-info/RECORD
