Metadata-Version: 2.1
Name: MyFirstPypi-pshpjr
Version: 0.1
Summary: Test Package
Home-page: https://github.com/pshpjr/Pypitest
Author: pshpjr
Author-email: pshpjr@naver.com
License: MIT
Download-URL: https://github.com/pshpjr/Pypitest/releases/tag/v0.1
Platform: UNKNOWN
Classifier: Programming Language :: Python :: 3
Classifier: Operating System :: OS Independent
Requires-Dist: pytest
